aliyun-akless-credential-provider-python-sdk/__init__.py
aliyun-sdk/__init__.py
pyszz/__init__.py
pyszz-2.2.dist-info/licenses/LICENSE.txt
quickMCP/__init__.py
whale-sdk/__init__.py
pyszz-2.2.dist-info/METADATA
pyszz-2.2.dist-info/WHEEL
pyszz-2.2.dist-info/top_level.txt
pyszz-2.2.dist-info/RECORD
