Metadata-Version: 2.4
Name: pyszz
Version: 2.2
Summary: pyszz
Home-page: 
Download-URL: 
Author: 
Author-email: 
License: MIT
Keywords: pyszz
Classifier: Intended Audience :: Developers
Classifier: Topic :: Software Development :: Build Tools
Classifier: License :: OSI Approved :: MIT License
Classifier: Programming Language :: Python :: 3
License-File: LICENSE.txt
Dynamic: classifier
Dynamic: keywords
Dynamic: license
Dynamic: license-file
Dynamic: summary
